priceofgold/__init__.py
livepriceofgold_usa_Rx168059-2024.0.0.3.5.dist-info/LICENSE
livepriceofgold_usa_Rx168059-2024.0.0.3.5.dist-info/METADATA
livepriceofgold_usa_Rx168059-2024.0.0.3.5.dist-info/WHEEL
livepriceofgold_usa_Rx168059-2024.0.0.3.5.dist-info/top_level.txt
livepriceofgold_usa_Rx168059-2024.0.0.3.5.dist-info/RECORD
